geolia/__about__.py
geolia/__init__.py
geolia/geometry.py
geolia/interp.py
geolia/mesh.py
geolia-0.0.1.dist-info/LICENSE.txt
geolia-0.0.1.dist-info/METADATA
geolia-0.0.1.dist-info/WHEEL
geolia-0.0.1.dist-info/top_level.txt
geolia-0.0.1.dist-info/RECORD
