Metadata-Version: 2.1
Name: geolia
Version: 0.0.1
Summary: Geometry and mesh tools
Author-email: Benjamin Vial <benjamin.vial84@gmail.com>
Maintainer-email: Benjamin Vial <benjamin.vial84@gmail.com>
License: GNU GENERAL PUBLIC LICENSE
Project-URL: Homepage, https://benvial.gitlab.io/geolia
Project-URL: Bug Reports, https://gitlab.com/benvial/geolia/issues
Project-URL: Source, https://gitlab.com/benvial/geolia
Keywords: geometry,mesh
Classifier: Development Status :: 4 - Beta
Classifier: Intended Audience :: Science/Research
Classifier: License :: OSI Approved :: GNU General Public License v3 or later (GPLv3+)
Classifier: Operating System :: OS Independent
Classifier: Programming Language :: Python
Classifier: Programming Language :: Python :: 3
Classifier: Programming Language :: Python :: 3.6
Classifier: Programming Language :: Python :: 3.7
Classifier: Programming Language :: Python :: 3.8
Classifier: Programming Language :: Python :: 3.9
Classifier: Programming Language :: Python :: 3.10
Classifier: Topic :: Scientific/Engineering
Classifier: Topic :: Scientific/Engineering :: Mathematics
Classifier: Topic :: Utilities
Requires-Python: >=3.8
License-File: LICENSE.txt
Requires-Dist: matplotlib
Requires-Dist: numpy
Requires-Dist: scipy
Requires-Dist: gmsh
Requires-Dist: meshio
Requires-Dist: h5py
Provides-Extra: dev
Requires-Dist: wheel ; extra == 'dev'
Requires-Dist: build ; extra == 'dev'
Requires-Dist: flake8 ; extra == 'dev'
Requires-Dist: black ; extra == 'dev'
Requires-Dist: twine ; extra == 'dev'
Requires-Dist: isort ; extra == 'dev'
Requires-Dist: radon ; extra == 'dev'
Requires-Dist: pydocstyle ; extra == 'dev'
Requires-Dist: pylint ; extra == 'dev'
Requires-Dist: pylint-json2html ; extra == 'dev'
Requires-Dist: python-gitlab ; extra == 'dev'
Requires-Dist: pip-tools ; extra == 'dev'
Provides-Extra: doc
Requires-Dist: sphinx ; extra == 'doc'
Requires-Dist: furo ; extra == 'doc'
Requires-Dist: sphinx-gallery ; extra == 'doc'
Requires-Dist: sphinx-copybutton ; extra == 'doc'
Requires-Dist: memory-profiler ; extra == 'doc'
Requires-Dist: numpydoc ; extra == 'doc'
Requires-Dist: sphinxcontrib-svg2pdfconverter ; extra == 'doc'
Requires-Dist: sphinxcontrib-bibtex ; extra == 'doc'
Requires-Dist: matplotlib ; extra == 'doc'
Requires-Dist: beautifulsoup4 ; extra == 'doc'
Requires-Dist: sphinx-autoapi ; extra == 'doc'
Requires-Dist: myst-parser ; extra == 'doc'
Requires-Dist: sphinx-design ; extra == 'doc'
Requires-Dist: sphinx-inline-tabs ; extra == 'doc'
Requires-Dist: sphinx-tabs ; extra == 'doc'
Requires-Dist: sphinx-autobuild ; extra == 'doc'
Provides-Extra: full
Requires-Dist: geolia[test] ; extra == 'full'
Requires-Dist: geolia[doc] ; extra == 'full'
Requires-Dist: geolia[dev] ; extra == 'full'
Provides-Extra: test
Requires-Dist: pytest ; extra == 'test'
Requires-Dist: pytest-cov ; extra == 'test'
Requires-Dist: pytest-datadir ; extra == 'test'
Requires-Dist: pytest-sugar ; extra == 'test'
Requires-Dist: pytest-xdist[psutil] ; extra == 'test'
Requires-Dist: coverage ; extra == 'test'
